{
  "searchTerm": "ai video",
  "timestamp": "2025-07-05T13:06:00.754Z",
  "app": {
    "title": "Viggle AI: Meme Generator",
    "description": "Official website: https://www.viggle.ai/. \nDiscord community: https://discord.gg/viggle.\n\nYou’ve seen Viggle everywhere on social media: the Joker/Lil Yachty stage entrance, the “gimme head top” trend, AI photo dances, and anyone playing football/NBA on TikTok—all created with Viggle AI. Experience AI video creation designed for everyone and bring your creative scenarios to life!\n\nHow to Use Viggle AI?\n- Upload a character image or your photo, select a motion template from our library, and generate your video. Within minutes, see yourself or your friends perfectly blended into captivating scenes! \n- For more control, upload both an image and a video to make the character mimic movements from your video - perfect for creating custom content. \n\nViggle's Must-try Features\n- Mix: replace anyone in a video. Upload one image and one video (or choose from our 1000+ fun templates).\n- Multi: Replace different characters in a video by uploading multiple character images. Dance with your friends, recreate a fighting scene, or act alongside your favorite movie star.\n- Mic: Lip sync, in an advanced way. Select music, type, or record yourself, let your character talk, sing, dance, and move, all at once. \n- Content feed: see what the community is creating and engage with the content you like by remixing. \n\nBest Use Cases of Viggle\n- Meme magic: Enjoy laughs with friends and family by transforming them into meme-worthy animations. Choose from 1000+ templates to create your own. \n- Make photos dance: Make yourself or anyone else dance like a pro by simply uploading a photo. \n- Play like a pro: upload your picture to experience your favorite football/NBA/NFL player's best moment. Tons of templates to have fun with!\n- Jump into movie scenes: Insert yourself into famous movie scenes and recreate iconic moments. \n- Animate your character as you like: you can act yourself, or find motion videos that will suit your character and your storyline. \n- Share the fun: Once you've created your video, share it easily across social media and watch them go viral, or with your friends to spread the joy. \n\nSupport and Community\n\nReach out to us at support@viggle.ai or leave feedback on our website and Discord community\nTerms of use: https://www.viggle.ai/terms-of-use\nPrivacy policy: https://www.viggle.ai/privacy-policy",
    "descriptionHTML": "Official website: https://www.viggle.ai/. <br>Discord community: https://discord.gg/viggle.<br><br>You’ve seen Viggle everywhere on social media: the Joker/Lil Yachty stage entrance, the “gimme head top” trend, AI photo dances, and anyone playing football/NBA on TikTok—all created with Viggle AI. Experience AI video creation designed for everyone and bring your creative scenarios to life!<br><br>How to Use Viggle AI?<br>- Upload a character image or your photo, select a motion template from our library, and generate your video. Within minutes, see yourself or your friends perfectly blended into captivating scenes! <br>- For more control, upload both an image and a video to make the character mimic movements from your video - perfect for creating custom content. <br><br>Viggle&#39;s Must-try Features<br>- Mix: replace anyone in a video. Upload one image and one video (or choose from our 1000+ fun templates).<br>- Multi: Replace different characters in a video by uploading multiple character images. Dance with your friends, recreate a fighting scene, or act alongside your favorite movie star.<br>- Mic: Lip sync, in an advanced way. Select music, type, or record yourself, let your character talk, sing, dance, and move, all at once. <br>- Content feed: see what the community is creating and engage with the content you like by remixing. <br><br>Best Use Cases of Viggle<br>- Meme magic: Enjoy laughs with friends and family by transforming them into meme-worthy animations. Choose from 1000+ templates to create your own. <br>- Make photos dance: Make yourself or anyone else dance like a pro by simply uploading a photo. <br>- Play like a pro: upload your picture to experience your favorite football/NBA/NFL player&#39;s best moment. Tons of templates to have fun with!<br>- Jump into movie scenes: Insert yourself into famous movie scenes and recreate iconic moments. <br>- Animate your character as you like: you can act yourself, or find motion videos that will suit your character and your storyline. <br>- Share the fun: Once you&#39;ve created your video, share it easily across social media and watch them go viral, or with your friends to spread the joy. <br><br>Support and Community<br><br>Reach out to us at support@viggle.ai or leave feedback on our website and Discord community<br>Terms of use: https://www.viggle.ai/terms-of-use<br>Privacy policy: https://www.viggle.ai/privacy-policy",
    "summary": "Swap anyone in a video",
    "installs": "5,000,000+",
    "minInstalls": 5000000,
    "maxInstalls": 5525117,
    "score": 4.746439,
    "scoreText": "4.7",
    "ratings": 88442,
    "reviews": [
      {
        "id": "8a2b6168-3c8f-43f7-886f-0d0838768f8a",
        "userName": "Muhammed Zayan",
        "userImage": "https://play-lh.googleusercontent.com/a-/ALV-UjVybka_5Btlr5xWxgxh24s1D4PKARgrFdCpdHfQfRNZzcGeei-Y",
        "date": "2025-02-26T18:08:34.891Z",
        "score": 5,
        "scoreText": "5",
        "url": "https://play.google.com/store/apps/details?id=com.warpengine.viggle&reviewId=8a2b6168-3c8f-43f7-886f-0d0838768f8a",
        "title": null,
        "text": "This app is awesome...like I could create lot of meme but the only one problem I'm facing is I can't save the video...even tho I saved it the video won't play and I can't even send it to someone cause no media can support the file it show it's like the file has some bug I've tried by installing and uninstall clearing cache it's not fixed yet",
        "replyDate": null,
        "replyText": null,
        "version": "1.2.3",
        "thumbsUp": 390,
        "criterias": []
      },
      {
        "id": "2931c204-432c-418e-bb06-afe438b3a1c2",
        "userName": "Madhubala singh",
        "userImage": "https://play-lh.googleusercontent.com/a/ACg8ocKjWb6QOUbQYyjydfINUQP9hdyfGh-jivxC2oKofKMywJwKdu0=mo",
        "date": "2025-01-30T17:04:07.715Z",
        "score": 5,
        "scoreText": "5",
        "url": "https://play.google.com/store/apps/details?id=com.warpengine.viggle&reviewId=2931c204-432c-418e-bb06-afe438b3a1c2",
        "title": null,
        "text": "I’ve been using Viggle for quite some time now, and I have to say, it’s an incredible AI that continues to impress me. When I first started using it, I was amazed by how intuitive and responsive it was. The AI’s ability to generate creative ideas, assist with my tasks, and provide thoughtful suggestions has truly elevated my experience.I’m excited to see how it evolves even further, and I’m confident it’ll continue to be a reliable and powerful Ai. Highly recommend 🌟",
        "replyDate": null,
        "replyText": null,
        "version": "1.2.3",
        "thumbsUp": 381,
        "criterias": []
      },
      {
        "id": "9ed02e03-ae59-4114-a9b7-b4d297223237",
        "userName": "Nate Collins",
        "userImage": "https://play-lh.googleusercontent.com/a-/ALV-UjXl-6nHwZ_MckRLieFMvYtbBT17yy5L_MBSO8qX9cLCRethJedl",
        "date": "2025-02-01T03:29:35.327Z",
        "score": 5,
        "scoreText": "5",
        "url": "https://play.google.com/store/apps/details?id=com.warpengine.viggle&reviewId=9ed02e03-ae59-4114-a9b7-b4d297223237",
        "title": null,
        "text": "I've only used it for a little bit and so far there are no ads and it does not ask you to give the money so I love it but I'm only for edits in we'll see if they surprise us with all that stuff we always delete the apps for in a minute",
        "replyDate": null,
        "replyText": null,
        "version": "1.2.3",
        "thumbsUp": 191,
        "criterias": []
      },
      {
        "id": "ca207209-c4d2-49c6-a4dc-e48740d662c9",
        "userName": "arifpavel Pavel",
        "userImage": "https://play-lh.googleusercontent.com/a/ACg8ocILSauoANA7oeH141pVtP7aItpW7IySlCKkQfUH7R5xYgzvoFo=mo",
        "date": "2025-02-21T13:07:40.923Z",
        "score": 5,
        "scoreText": "5",
        "url": "https://play.google.com/store/apps/details?id=com.warpengine.viggle&reviewId=ca207209-c4d2-49c6-a4dc-e48740d662c9",
        "title": null,
        "text": "Man this app is just amazing. It is the best ai I've ever used. You can simply exchange characters with this amazing tool. And the best part is it is completely free and no ads. The watermark can be a problem but this is not a big problem cuz it is completely free so I recommend you this app",
        "replyDate": null,
        "replyText": null,
        "version": "1.2.3",
        "thumbsUp": 183,
        "criterias": [
          {
            "criteria": "vaf_phase1_hd_movies_shows",
            "rating": 2
          },
          {
            "criteria": "vaf_phase1_android_tv",
            "rating": 2
          },
          {
            "criteria": "vaf_phase1_closed_captions",
            "rating": 2
          }
        ]
      },
      {
        "id": "868e89e3-bb30-4840-be9a-1a1daaca4a46",
        "userName": "Kade Phoenix",
        "userImage": "https://play-lh.googleusercontent.com/a-/ALV-UjWBrmwQpP4zW4CFY9r5MaZaeQEJ4KkAW2HQBvLFoJeQXjmX2ew",
        "date": "2025-02-07T15:26:49.740Z",
        "score": 4,
        "scoreText": "4",
        "url": "https://play.google.com/store/apps/details?id=com.warpengine.viggle&reviewId=868e89e3-bb30-4840-be9a-1a1daaca4a46",
        "title": null,
        "text": "Best ai I ever stumbled on I use this app to make my parents and friends do silly dances and we all laugh but there's one issue the videos take so long to play sometimes when it plays once it rests and takes so long to play it again sometimes it doesn't let me make videos but overall I give it a 4 star rating and they should fix the internet issue like sometimes I LITTERELY SIT NEXT TO THE WIFI AND STILL DOESN'T WORK and they should fix that",
        "replyDate": null,
        "replyText": null,
        "version": "1.2.3",
        "thumbsUp": 137,
        "criterias": []
      },
      {
        "id": "0fd7fdc8-5bf6-4232-bd9f-e91ea885225a",
        "userName": "Xandra Muñoz",
        "userImage": "https://play-lh.googleusercontent.com/a-/ALV-UjU6EQUDmi7HjlZ2HUCoDG7zEiwBbR2tXL9V5pBXydAyhq9_s4QU",
        "date": "2025-03-13T07:11:10.866Z",
        "score": 4,
        "scoreText": "4",
        "url": "https://play.google.com/store/apps/details?id=com.warpengine.viggle&reviewId=0fd7fdc8-5bf6-4232-bd9f-e91ea885225a",
        "title": null,
        "text": "While the app truly does serve its purpose with great quality and a reasonable condition, I do hope that the moderation should be more strict. A lot of unwanted things pop up as \"recommended,\" and the video does not serve anything but troll. Searching for a fun template and diving too deep, I came across a few gruesome content.",
        "replyDate": null,
        "replyText": null,
        "version": "1.2.4",
        "thumbsUp": 127,
        "criterias": [
          {
            "criteria": "vaf_apps_attribute_download_for_offline_viewing_v2",
            "rating": 1
          },
          {
            "criteria": "vaf_phase1_buying_tickets",
            "rating": 2
          },
          {
            "criteria": "vaf_apps_attribute_soccer_v2",
            "rating": 2
          }
        ]
      },
      {
        "id": "48c827a5-741a-4021-9ace-9cc79d547a32",
        "userName": "Ismail",
        "userImage": "https://play-lh.googleusercontent.com/a-/ALV-UjWGhAqF-qmTPE20r7xlj5v4s7apv4gGYgJraZ-VV7o9MT8oaxc",
        "date": "2025-05-19T18:50:00.805Z",
        "score": 4,
        "scoreText": "4",
        "url": "https://play.google.com/store/apps/details?id=com.warpengine.viggle&reviewId=48c827a5-741a-4021-9ace-9cc79d547a32",
        "title": null,
        "text": "it incredibly easy to use and extremely useful to make videos. it blowes my mind the way it instantly adds people into any video i want it to. the only problem is it freezes quite a bit and is really laggy but for what the app does it is worth it",
        "replyDate": null,
        "replyText": null,
        "version": "1.3.0",
        "thumbsUp": 116,
        "criterias": [
          {
            "criteria": "vaf_apps_attribute_soccer_v1",
            "rating": 1
          },
          {
            "criteria": "vaf_phase1_buying_tickets",
            "rating": 2
          },
          {
            "criteria": "vaf_phase1_hd_movies_shows",
            "rating": 1
          }
        ]
      },
      {
        "id": "9a67c8ae-1191-4b01-9a1d-889b4164054f",
        "userName": "Aarav Goyal",
        "userImage": "https://play-lh.googleusercontent.com/a-/ALV-UjUe5LHD0Dig_kxap_KVk-KEe96LT2Px2wYdQd0HkgFqoF3beUAv",
        "date": "2025-06-08T07:58:56.896Z",
        "score": 5,
        "scoreText": "5",
        "url": "https://play.google.com/store/apps/details?id=com.warpengine.viggle&reviewId=9a67c8ae-1191-4b01-9a1d-889b4164054f",
        "title": null,
        "text": "litterly the most fun app!!! we can generate ANY ai video and its all free totally*!!!!🤑 we just need to wait for 10 minutes when we want to create a video, except for the 1st time we download this app, 10 minutes is completely worth the wait , considering how much good and safe and convient features this app has.🗿👌 This app has been way too much fun, i really enjoy it and recommend others to give it a try too🔥",
        "replyDate": null,
        "replyText": null,
        "version": "1.3.2",
        "thumbsUp": 102,
        "criterias": [
          {
            "criteria": "vaf_phase1_google_cast",
            "rating": 3
          },
          {
            "criteria": "vaf_phase1_android_tv",
            "rating": 3
          },
          {
            "criteria": "vaf_phase1_reviews_by_critics",
            "rating": 3
          }
        ]
      },
      {
        "id": "a5a05f83-7ce3-4ff7-9567-2f14ffc9d13b",
        "userName": "Dave Price",
        "userImage": "https://play-lh.googleusercontent.com/a-/ALV-UjXfJ5wymocwsv-cRXIWb63lYGWJWMVwUfqZjktbxsUMXhXbkSZGgQ",
        "date": "2025-06-07T23:18:08.489Z",
        "score": 5,
        "scoreText": "5",
        "url": "https://play.google.com/store/apps/details?id=com.warpengine.viggle&reviewId=a5a05f83-7ce3-4ff7-9567-2f14ffc9d13b",
        "title": null,
        "text": "Support: Been using this app for a while no worries. now when I try to download video it gets to 99% then crashes. just letting you know.",
        "replyDate": null,
        "replyText": null,
        "version": "1.3.2",
        "thumbsUp": 78,
        "criterias": []
      },
      {
        "id": "6bb05451-2393-451c-845d-6e2222cd4fe2",
        "userName": "Kiran Gurung",
        "userImage": "https://play-lh.googleusercontent.com/a/ACg8ocKDm3XDUTiw_VyS3UyJQWvWeDvL6TmmMTsfUaMdKmEAQBMKdw=mo",
        "date": "2025-05-25T14:47:54.257Z",
        "score": 5,
        "scoreText": "5",
        "url": "https://play.google.com/store/apps/details?id=com.warpengine.viggle&reviewId=6bb05451-2393-451c-845d-6e2222cd4fe2",
        "title": null,
        "text": "this app is better than others app but sometimes it make some lag or error and we cannot put images videos. so,it should be fixed in upcoming days. Thank you 😊",
        "replyDate": null,
        "replyText": null,
        "version": "1.3.0",
        "thumbsUp": 70,
        "criterias": []
      }
    ],
    "histogram": {
      "1": 1485,
      "2": 486,
      "3": 3268,
      "4": 8293,
      "5": 74827
    },
    "price": 0,
    "free": true,
    "currency": "USD",
    "priceText": "Free",
    "available": true,
    "offersIAP": true,
    "IAPRange": "$2.99 - $749.99 per item",
    "androidVersion": "7.0",
    "androidVersionText": "7.0",
    "androidMaxVersion": "VARY",
    "developer": "WarpEngine",
    "developerId": "WarpEngine",
    "developerEmail": "support@viggle.ai",
    "developerWebsite": "https://www.viggle.ai/",
    "developerLegalName": "Warpengine Canada Inc",
    "developerLegalEmail": "support@viggle.ai",
    "developerLegalAddress": "1910-10 Capreol Crt, Toronto, ON M5V 4B3, Canada",
    "developerLegalPhoneNumber": "+1 647-627-8109",
    "privacyPolicy": "https://viggle.ai/privacy-policy",
    "developerInternalID": "WarpEngine",
    "genre": "Entertainment",
    "genreId": "ENTERTAINMENT",
    "categories": [
      {
        "name": "Entertainment",
        "id": "ENTERTAINMENT"
      }
    ],
    "icon": "https://play-lh.googleusercontent.com/Lo9FDGAXWen8n2NhpJyMGnaXpsJa-QWahWZx_BoTtzTpMhFCLVN_TWpLzKGD-oCo9pnG",
    "headerImage": "https://play-lh.googleusercontent.com/VhSBOZ7tOIy4ZeT5a0-MUMOPQoi7ulrCHLpjDJ6BMu-dXaiVjLox3tzQokZqD6-SQYE",
    "screenshots": [
      "https://play-lh.googleusercontent.com/MBpPYEQDqsFDyfjzN30-CfY-n9HYV4i3M4JJg9eVoxnI_h0nBm0DBkPMYWtmm0oG2_Gz",
      "https://play-lh.googleusercontent.com/SDsoQb3E0aysJmQTazdxL3RFN-MAYdQDVXoPSBY_0ovLTWvHlnN6SEkGHkbtix4RAg",
      "https://play-lh.googleusercontent.com/QJMfQ-5uJO9s_JnQE_uT0lNNK8WViDRYLZjfaW5KjY9-peUmt_OqyL2NMNIZLd_Mtg",
      "https://play-lh.googleusercontent.com/RSWIyjSYM2o61dOAKTAcEZqf18yx1PlMt7uYaDUAy48tydxOA8TDKXeuGohcL2I5mc4g",
      "https://play-lh.googleusercontent.com/wkFU54rJJOR_8noqNZuKyU8zb6-UTk3u71JWhs1kWzGU0Be14hOl5_TVtRPjyDTrQhY",
      "https://play-lh.googleusercontent.com/9ZZeCzs9tqNjlryQbez9O_2ttWEcTpqQTSUQ8VaFSXgwtOIb8O-RuF_ncikE7x1y-24",
      "https://play-lh.googleusercontent.com/Lz84mBQO2ypEPCqMjKptBu9uXCuRR1lFqO19Ll6O32nPyaM4ihwAYZ9J3pkLjneaHA",
      "https://play-lh.googleusercontent.com/CPjJ8s2EnlYZB55K73cAjzLLuILwiN4GoFeCvwLzEZ-o8lKPnOrocNhRTp1k5aQb5R4",
      "https://play-lh.googleusercontent.com/2to7nAC-HkHs_vEXAuTsoA7XzuhIl-B7grhrzREKgMKWJKNvUw2QNoZzx6PS7SNY9ME",
      "https://play-lh.googleusercontent.com/V2DAHEGYeoZ_TkrImzBOGchBB-Uo7cZf61I5XafBVd3NBX0FRTo9Yf7ZLzf_ly2v3PVO",
      "https://play-lh.googleusercontent.com/k5IHkVqUdlkUYMfUi8nLB_sX-fWFy6KVCYvh4mzYsQYqvbO7I-5dwZaqTOXpoWx49BY",
      "https://play-lh.googleusercontent.com/XiFAG783YN5pAw2JKh6s8Mv1OxVbH3GRHz_evA09qZw31mLLlL4SqoNcz6xkuVKcNNI",
      "https://play-lh.googleusercontent.com/ovtQm-w-O_6jUbIyYP2Qod3CqmbMZIL4UIVgUHag7kvRDylWGWe6j0WmSDC-Hj2nCBY",
      "https://play-lh.googleusercontent.com/sGKBbQI63ryy7EUGFQ-8ReIdpeEGt0jDw5LSgE2iyKv05ID6-pFpdOXU3RznuALiq_Ll",
      "https://play-lh.googleusercontent.com/YG4sy6DFJ9n2YtfeypB6PKGPoX99jTpiMcP5ssErjDlSP0ePk_yL7z5lkqQBTnT0JdE",
      "https://play-lh.googleusercontent.com/2JKBbTIU_Mjxa00L1RNLqUEkk4rpTVOubf8On78ek1olFx1HKv1m0mSSt_OJBYL1Sg",
      "https://play-lh.googleusercontent.com/_gi7Ch33tTj4FUKaPUd0KAD5OFC64D_REzlM2yJFa2-u84R8NAATxcSvRN5SmLNNlS87",
      "https://play-lh.googleusercontent.com/Oi2RIdeql2tPKh4DNy4nUmPrpwzHWdHn1SRm5TpavFUmNaPMM_zCyRpnImcYWX9GDw",
      "https://play-lh.googleusercontent.com/gs88UzwoZCxdYZlOGHajDFswPgDlIIYjYNfPD-6f9Q9cz3_DDo5dVrRG4mRYlUwzsXY",
      "https://play-lh.googleusercontent.com/DcZ7wazcrJ8Ta_1HnH_9fdxck-Gcw4PZOg8a3wuLBfaeBksbIjByqUCZp5aaFYtOZzc",
      "https://play-lh.googleusercontent.com/J61zPl0Hml9wX95sTOooix0dmegULnPQ-Yj2lpfg8sZPcY07vPVGcJMGx-wvbcJnJOA"
    ],
    "contentRating": "Everyone",
    "adSupported": true,
    "released": "Aug 13, 2024",
    "updated": 1748515049000,
    "version": "1.3.2",
    "comments": [],
    "preregister": false,
    "earlyAccessEnabled": false,
    "isAvailableInPlayPass": false,
    "appId": "com.warpengine.viggle",
    "url": "https://play.google.com/store/apps/details?id=com.warpengine.viggle&hl=en&gl=us",
    "AIReview": "<h2>Viggle AI: Meme Generator – App Review</h2>\n<h2>Overview</h2>\n<p>Viggle AI: Meme Generator has exploded onto the scene, capitalizing on the current obsession with AI-generated content and internet memes. With over 5.5 million installs and a robust 4.746 rating, it&#39;s clear this app is tapping into something significant within the social media landscape. The core concept – using an AI to transform user photos and videos into viral-ready meme formats – is undeniably appealing, particularly for younger demographics actively engaged in TikTok, Instagram Reels, and other short-form video platforms.  The app’s success hinges on its ability to deliver consistently engaging results and maintain a user base amidst the rapid evolution of online trends. The official website and Discord community provide avenues for support and further engagement, indicating Viggle AI&#39;s commitment to fostering a dedicated user group.</p>\n<h2>Key Features</h2>\n<ul>\n<li><strong>AI-Powered Video Generation:</strong> This is the app’s headline feature and its core value proposition. Users upload an image (typically a selfie or chosen character) and select from a library of motion templates designed for various meme formats.</li>\n<li><strong>Motion Template Library:</strong> The app boasts a surprisingly diverse range of motion templates, categorized by style (e.g., dance, reaction, dramatic, silly). These templates are the engine behind transforming static images into dynamic video memes.  The selection isn’t exhaustive but covers popular trends and provides enough variety to keep users experimenting.</li>\n<li><strong>Swap Anyone Functionality:</strong> A key element of the app&#39;s appeal is its ability to &quot;swap anyone&quot; in a video. This functionality allows for creative transformations, placing your face onto existing videos or applying different character movements to your own footage.</li>\n<li><strong>Simple Interface:</strong> The interface is remarkably intuitive.  The process – upload photo -&gt; select template -&gt; generate video – is streamlined and requires minimal technical expertise. </li>\n<li><strong>Social Sharing:</strong> Direct integration with major social media platforms (TikTok, Instagram, Facebook) allows for immediate sharing of generated memes.</li>\n</ul>\n<h2>Strengths</h2>\n<ul>\n<li><strong>Viral Potential:</strong> The app’s primary strength lies in its ability to quickly produce meme-worthy content.  The ease of use and the AI&#39;s creative capabilities drastically reduce the time and effort required to create engaging videos that have a high chance of going viral.</li>\n<li><strong>Large User Base &amp; Social Proof:</strong> With 5.5 million installs and a high rating, Viggle AI benefits from significant social proof. This creates a sense of community and encourages new users to try it out.  The popularity is demonstrably reflected in the prevalence of its meme formats across platforms like TikTok.</li>\n<li><strong>Intuitive User Experience:</strong> The app’s simple, uncluttered interface makes it accessible to virtually anyone, regardless of their video editing experience. No prior knowledge or technical skills are required. </li>\n<li><strong>Active Community Support:</strong>  The presence of a Discord community provides users with support, feedback opportunities, and a place to share their creations. This fosters engagement and helps the app adapt to user preferences.</li>\n</ul>\n<h2>Areas for Improvement</h2>\n<ul>\n<li><strong>Template Variety Expansion:</strong> While the current motion template library is decent, expanding it significantly would dramatically increase the app&#39;s long-term appeal.  The addition of more niche templates aligned with emerging trends would be a major benefit.</li>\n<li><strong>AI Refinement:</strong> The quality of the AI-generated videos can sometimes be inconsistent. Some outputs look remarkably polished while others appear somewhat robotic or unnatural. Refining the AI algorithm to produce consistently higher-quality results is crucial.</li>\n<li><strong>Advanced Editing Options:</strong> The app currently lacks more advanced editing features, such as manual adjustments to timing, transitions, and audio integration. Introducing basic editing tools would appeal to a wider audience looking for more control over their creations.</li>\n<li><strong>Monetization Strategy (Beyond Free):</strong> While the free version is appealing, offering premium templates or functionalities through a subscription model could provide a sustainable revenue stream without alienating existing users.</li>\n</ul>\n<h2>User Experience</h2>\n<p>The user experience of Viggle AI is remarkably smooth and enjoyable. The onboarding process is simple; immediately upon launching the app, users are guided through uploading an image and selecting a template.  Generating a video takes mere seconds – a crucial factor given the fast-paced nature of online trends. Navigating the interface is intuitive, with clearly labeled buttons and options. The direct social media sharing integration is seamless, allowing users to instantly post their creations to their preferred platforms. However, as noted previously, the occasional inconsistencies in AI output can disrupt the flow slightly, particularly when attempting complex or highly stylized meme formats.</p>\n<h2>Value for Money</h2>\n<p>Viggle AI operates on a completely free model. This is a significant advantage given its popularity and the low barrier to entry.  The app’s value lies entirely in its ability to provide users with a tool that facilitates the creation of engaging, shareable content—essentially offering a ‘viral-potential generator’.  While a premium subscription option could be introduced, the current free model is highly effective at attracting and retaining a large user base.</p>\n<h2>Conclusion</h2>\n<p>Viggle AI: Meme Generator has achieved remarkable success by tapping into a powerful trend – the desire for easy, viral meme creation. Its intuitive interface, coupled with its AI-powered video generation capabilities, makes it accessible to anyone looking to create entertaining content. While opportunities remain for improvement—particularly in expanding the template library and refining the AI&#39;s output—the app’s current strengths far outweigh its weaknesses.  With a large and engaged user base fueled by social media buzz, Viggle AI is likely to remain a prominent player in the evolving landscape of online meme culture. It represents a clever application of AI technology for creative expression and offers significant value to users seeking quick and engaging video content.</p>"
  }
}